CHANGELOG.rst
COPYING
COPYING.LESSER
MANIFEST.in
README.rst
createdb.py
setup.py
apache/fmn.web.conf
apache/fmn.web.wsgi
fedmsg.d/base.py
fedmsg.d/endpoints.py
fedmsg.d/fas_credentials.py
fedmsg.d/fmn.py
fedmsg.d/fmn.pyc
fedmsg.d/logging.py
fedmsg.d/ssl.py
fmn/__init__.py
fmn.web.egg-info/PKG-INFO
fmn.web.egg-info/SOURCES.txt
fmn.web.egg-info/dependency_links.txt
fmn.web.egg-info/namespace_packages.txt
fmn.web.egg-info/not-zip-safe
fmn.web.egg-info/pbr.json
fmn.web.egg-info/requires.txt
fmn.web.egg-info/top_level.txt
fmn/web/__init__.py
fmn/web/app.py
fmn/web/converters.py
fmn/web/default_config.py
fmn/web/forms.py
fmn/web/main.py
fmn/web/docs/about.rst
fmn/web/static/bootstrap-3.0.1-dist/css/bootstrap-theme.css
fmn/web/static/bootstrap-3.0.1-dist/css/bootstrap-theme.min.css
fmn/web/static/bootstrap-3.0.1-dist/css/bootstrap.css
fmn/web/static/bootstrap-3.0.1-dist/css/bootstrap.min.css
fmn/web/static/bootstrap-3.0.1-dist/fonts/glyphicons-halflings-regular.eot
fmn/web/static/bootstrap-3.0.1-dist/fonts/glyphicons-halflings-regular.svg
fmn/web/static/bootstrap-3.0.1-dist/fonts/glyphicons-halflings-regular.ttf
fmn/web/static/bootstrap-3.0.1-dist/fonts/glyphicons-halflings-regular.woff
fmn/web/static/bootstrap-3.0.1-dist/js/bootstrap.js
fmn/web/static/bootstrap-3.0.1-dist/js/bootstrap.min.js
fmn/web/static/bootstrap-3.0.2-fedora/css/bootstrap-theme.css
fmn/web/static/bootstrap-3.0.2-fedora/css/bootstrap-theme.min.css
fmn/web/static/bootstrap-3.0.2-fedora/css/bootstrap.css
fmn/web/static/bootstrap-3.0.2-fedora/css/bootstrap.min.css
fmn/web/static/bootstrap-3.0.2-fedora/fonts/glyphicons-halflings-regular.eot
fmn/web/static/bootstrap-3.0.2-fedora/fonts/glyphicons-halflings-regular.svg
fmn/web/static/bootstrap-3.0.2-fedora/fonts/glyphicons-halflings-regular.ttf
fmn/web/static/bootstrap-3.0.2-fedora/fonts/glyphicons-halflings-regular.woff
fmn/web/static/bootstrap-3.0.2-fedora/js/bootstrap.js
fmn/web/static/bootstrap-3.0.2-fedora/js/bootstrap.min.js
fmn/web/static/bootstrap-3.1.1-fedora/css/bootstrap-theme.css
fmn/web/static/bootstrap-3.1.1-fedora/css/bootstrap-theme.css.map
fmn/web/static/bootstrap-3.1.1-fedora/css/bootstrap-theme.min.css
fmn/web/static/bootstrap-3.1.1-fedora/css/bootstrap.css
