Metadata-Version: 1.1
Name: fmn.web
Version: 0.7.1
Summary: Frontend Web Application for Fedora Notifications
Home-page: https://github.com/fedora-infra/fmn.web/
Author: Ralph Bean
Author-email: rbean@redhat.com
License: LGPLv2+
Download-URL: https://pypi.python.org/pypi/fmn.web/
Platform: UNKNOWN
Classifier: Environment :: Web Environment
Classifier: Topic :: Software Development :: Libraries :: Python Modules
Classifier: Intended Audience :: Developers
Classifier: Programming Language :: Python
